mr_star_ble/__init__.py
mr_star_ble/api.py
mr_star_ble/color.py
mr_star_ble/commands.py
mr_star_ble/const.py
mr_star_ble/discover.py
mr_star_ble/int.py
mr_star_ble/transition/__init__.py
mr_star_ble/transition/animate.py
mr_star_ble/transition/diff.py
mr_star_ble/transition/frame.py
mr_star_ble/transition/tween.py
mr_star_ble-0.4.1.dist-info/METADATA
mr_star_ble-0.4.1.dist-info/WHEEL
mr_star_ble-0.4.1.dist-info/top_level.txt
mr_star_ble-0.4.1.dist-info/RECORD
