Metadata-Version: 2.1
Name: mr_star_ble
Version: 0.4.1
Summary: Integrating MR Star light into Python
Author-email: Mikhael Khrustik <misha@myrt.co>
License: MIT
Keywords: light,led,bleak
Classifier: Development Status :: 5 - Production/Stable
Classifier: Intended Audience :: Developers
Classifier: License :: OSI Approved :: MIT License
Classifier: Programming Language :: Python :: 3.10
Classifier: Programming Language :: Python :: 3.11
Classifier: Programming Language :: Python :: 3.12
Requires-Python: >=3.10
Requires-Dist: bleak
